candle_data_manager/Architecture - CandleDataManager.md
candle_data_manager/__init__.py
candle_data_manager/API/__init__.py
candle_data_manager/API/CandleDataAPI/CandleDataAPI.py
candle_data_manager/API/CandleDataAPI/__init__.py
candle_data_manager/API/CandleDataAPI/for-agent-moduleinfo.md
candle_data_manager/Core/__init__.py
candle_data_manager/Core/for-agent-moduleinfo.md
candle_data_manager/Core/CandleFetcher/Architecture - CandleFetcher.md
candle_data_manager/Core/CandleFetcher/__init__.py
candle_data_manager/Core/CandleFetcher/API/for-agent-moduleinfo.md
candle_data_manager/Core/CandleFetcher/API/CandleFetcher/CandleFetcher.py
candle_data_manager/Core/CandleFetcher/API/CandleFetcher/for-agent-moduleinfo.md
candle_data_manager/Core/CandleFetcher/Core/__init__.py
candle_data_manager/Core/CandleFetcher/Core/for-agent-moduleinfo.md
candle_data_manager/Core/CandleFetcher/Core/TimeConverter/TimeConverter.py
candle_data_manager/Core/CandleFetcher/Core/TimeConverter/__init__.py
candle_data_manager/Core/CandleFetcher/Core/TimeConverter/for-agent-moduleinfo.md
candle_data_manager/Core/CandleFetcher/Plugin/BinanceFuturesProvider.py
candle_data_manager/Core/CandleFetcher/Plugin/BinanceSpotProvider.py
candle_data_manager/Core/CandleFetcher/Plugin/FdrProvider.py
candle_data_manager/Core/CandleFetcher/Plugin/UpbitProvider.py
candle_data_manager/Core/CandleFetcher/Plugin/for-agent-moduleinfo.md
candle_data_manager/Core/CandleFetcher/Plugin/FdrProvider/for-agent-moduleinfo.md
candle_data_manager/Core/CandleFetcher/Service/__init__.py
candle_data_manager/Core/CandleFetcher/Service/for-agent-moduleinfo.md
candle_data_manager/Core/CandleFetcher/Service/ApiValidationService/ApiValidationService.py
candle_data_manager/Core/CandleFetcher/Service/ApiValidationService/for-agent-moduleinfo.md
candle_data_manager/Core/CandleFetcher/Service/NormalizationService/NormalizationService.py
candle_data_manager/Core/CandleFetcher/Service/NormalizationService/__init__.py
candle_data_manager-0.1.1.dist-info/METADATA
candle_data_manager-0.1.1.dist-info/WHEEL
candle_data_manager-0.1.1.dist-info/licenses/LICENSE
candle_data_manager-0.1.1.dist-info/RECORD
