Metadata-Version: 2.4
Name: candle-data-manager
Version: 0.1.1
Summary: Fetch, store, and manage OHLCV candle data from cryptocurrency exchanges (Binance, Upbit) with MySQL storage
Project-URL: Homepage, https://gatesplan-mathgate.com
Project-URL: Repository, https://github.com/gatesplan/candle-data-manager
Project-URL: Issues, https://github.com/gatesplan/candle-data-manager/issues
Author-email: fishfactory <gatesplan@gmail.com>
License: MIT License
License-File: LICENSE
Classifier: Operating System :: OS Independent
Classifier: Programming Language :: Python :: 3
Classifier: Programming Language :: Python :: 3.10
Classifier: Programming Language :: Python :: 3.11
Classifier: Programming Language :: Python :: 3.12
Requires-Python: >=3.10
Requires-Dist: binance-connector>=3.0.0
Requires-Dist: finance-datareader>=0.9.0
Requires-Dist: loguru>=0.7.0
Requires-Dist: numpy>=1.24.0
Requires-Dist: pandas>=2.0.0
Requires-Dist: pymysql>=1.0.0
Requires-Dist: python-dotenv>=1.0.0
Requires-Dist: pyupbit>=0.2.0
Requires-Dist: requests>=2.28.0
Requires-Dist: sqlalchemy>=2.0.0
Provides-Extra: dev
Requires-Dist: black>=23.0; extra == 'dev'
Requires-Dist: pytest-cov>=4.0; extra == 'dev'
Requires-Dist: pytest>=7.0; extra == 'dev'
Requires-Dist: ruff>=0.1.0; extra == 'dev'
